histplotlib/__about__.py
histplotlib/__init__.py
histplotlib-0.0.1.dist-info/METADATA
histplotlib-0.0.1.dist-info/WHEEL
histplotlib-0.0.1.dist-info/licenses/LICENSE.txt
histplotlib-0.0.1.dist-info/RECORD
